{
  "race_id": "musselburgh-2026-02-15-16-50",
  "meta": {
    "track": "Musselburgh",
    "date": "2026-02-15",
    "off_time": "16:50",
    "distance": "2m3f171y",
    "going": "good",
    "race_class": "5",
    "race_name": "Virgin Bet Conditional Jockeys' Handicap Hurdle",
    "runners_count": 6
  },
  "runners": [
    {
      "rank": 1,
      "runner_name": "Cher Tara",
      "number": 2,
      "draw": null,
      "age": 7,
      "weight": "11-11",
      "official_rating": 96,
      "jockey": "Toby McCain-Mitchell",
      "trainer": "D Bourke",
      "odds_decimal": 4.5,
      "total_score": 57.3,
      "components": [
        {
          "name": "Market",
          "score": 31.1,
          "weight": 0.35,
          "weighted_score": 10.88,
          "reason": "Odds 4.5 (implied 22.2%)"
        },
        {
          "name": "Rating",
          "score": 100.0,
          "weight": 0.25,
          "weighted_score": 25.0,
          "reason": "OR 96 (field range 81-96)"
        },
        {
          "name": "Form",
          "score": 38.3,
          "weight": 0.2,
          "weighted_score": 7.66,
          "reason": "Recent positions: 3/7/5/9/3/6 (recency-weighted avg)"
        },
        {
          "name": "Suitability",
          "score": 75.0,
          "weight": 0.15,
          "weighted_score": 11.25,
          "reason": "4/6 runs at similar distance; 3/6 runs on similar going; 1/6 runs at Musselburgh"
        },
        {
          "name": "Connections",
          "score": 50.0,
          "weight": 0.05,
          "weighted_score": 2.5,
          "reason": "Connections: J: Toby McCain-Mitchell, T: D Bourke (no win-rate stats available; neutral score)"
        }
      ],
      "recent_form": [
        {
          "position": 3,
          "date": "2026-01-15",
          "distance": "2m4f62y",
          "going": "good",
          "race_class": "5",
          "track": "Newcastle"
        },
        {
          "position": 7,
          "date": "2025-12-22",
          "distance": "2m7f180y",
          "going": "good",
          "race_class": "5",
          "track": "Musselburgh"
        },
        {
          "position": 5,
          "date": "2025-11-12",
          "distance": "2m3f110y",
          "going": "soft",
          "race_class": "5",
          "track": "Ayr"
        },
        {
          "position": 9,
          "date": "2025-10-31",
          "distance": "3m30y",
          "going": "good",
          "race_class": "",
          "track": "Down Royal"
        },
        {
          "position": 3,
          "date": "2025-10-21",
          "distance": "2m4f35y",
          "going": "soft",
          "race_class": "4",
          "track": "Perth"
        },
        {
          "position": 6,
          "date": "2025-10-04",
          "distance": "2m4f50y",
          "going": "soft",
          "race_class": "",
          "track": "Gowran Park"
        }
      ]
    },
    {
      "rank": 2,
      "runner_name": "Gonnino",
      "number": 3,
      "draw": null,
      "age": 7,
      "weight": "11-9",
      "official_rating": 94,
      "jockey": "Dylan Johnston",
      "trainer": "Gary Rutherford",
      "odds_decimal": 8.5,
      "total_score": 54.5,
      "components": [
        {
          "name": "Market",
          "score": 16.5,
          "weight": 0.35,
          "weighted_score": 5.77,
          "reason": "Odds 8.5 (implied 11.8%)"
        },
        {
          "name": "Rating",
          "score": 93.3,
          "weight": 0.25,
          "weighted_score": 23.32,
          "reason": "OR 94 (field range 81-96)"
        },
        {
          "name": "Form",
          "score": 57.1,
          "weight": 0.2,
          "weighted_score": 11.42,
          "reason": "Recent positions: 6/2/4/2/4 (recency-weighted avg)"
        },
        {
          "name": "Suitability",
          "score": 76.7,
          "weight": 0.15,
          "weighted_score": 11.51,
          "reason": "2/6 runs at similar distance; 5/6 runs on similar going; 2/6 runs at Musselburgh"
        },
        {
          "name": "Connections",
          "score": 50.0,
          "weight": 0.05,
          "weighted_score": 2.5,
          "reason": "Connections: J: Dylan Johnston, T: Gary Rutherford (no win-rate stats available; neutral score)"
        }
      ],
      "recent_form": [
        {
          "position": 6,
          "date": "2025-12-22",
          "distance": "1m7f124y",
          "going": "good",
          "race_class": "5",
          "track": "Musselburgh"
        },
        {
          "position": 2,
          "date": "2025-12-08",
          "distance": "1m7f124y",
          "going": "soft",
          "race_class": "5",
          "track": "Musselburgh"
        },
        {
          "position": null,
          "date": "2025-11-08",
          "distance": "2m4f189y",
          "going": "good",
          "race_class": "5",
          "track": "Kelso"
        },
        {
          "position": 4,
          "date": "2025-06-08",
          "distance": "2m47y",
          "going": "good",
          "race_class": "5",
          "track": "Perth"
        },
        {
          "position": 2,
          "date": "2025-05-15",
          "distance": "2m47y",
          "going": "good",
          "race_class": "4",
          "track": "Perth"
        },
        {
          "position": 4,
          "date": "2025-04-07",
          "distance": "2m2f25y",
          "going": "good",
          "race_class": "4",
          "track": "Kelso"
        }
      ]
    },
    {
      "rank": 3,
      "runner_name": "National Question",
      "number": 6,
      "draw": null,
      "age": 6,
      "weight": "10-12",
      "official_rating": 83,
      "jockey": "Joshua Thompson",
      "trainer": "A Nicol",
      "odds_decimal": 3.75,
      "total_score": 53.6,
      "components": [
        {
          "name": "Market",
          "score": 37.3,
          "weight": 0.35,
          "weighted_score": 13.05,
          "reason": "Odds 3.8 (implied 26.7%)"
        },
        {
          "name": "Rating",
          "score": 56.7,
          "weight": 0.25,
          "weighted_score": 14.18,
          "reason": "OR 83 (field range 81-96)"
        },
        {
          "name": "Form",
          "score": 66.9,
          "weight": 0.2,
          "weighted_score": 13.38,
          "reason": "Recent positions: 1/5/2/1/8/5 (recency-weighted avg)"
        },
        {
          "name": "Suitability",
          "score": 70.0,
          "weight": 0.15,
          "weighted_score": 10.5,
          "reason": "1/6 runs at similar distance; 4/6 runs on similar going; 2/6 runs at Musselburgh"
        },
        {
          "name": "Connections",
          "score": 50.0,
          "weight": 0.05,
          "weighted_score": 2.5,
          "reason": "Connections: J: Joshua Thompson, T: A Nicol (no win-rate stats available; neutral score)"
        }
      ],
      "recent_form": [
        {
          "position": 1,
          "date": "2026-01-25",
          "distance": "2m3f188y",
          "going": "good",
          "race_class": "5",
          "track": "Sedgefield"
        },
        {
          "position": 5,
          "date": "2025-12-22",
          "distance": "1m7f124y",
          "going": "good",
          "race_class": "5",
          "track": "Musselburgh"
        },
        {
          "position": 2,
          "date": "2025-11-13",
          "distance": "2m178y",
          "going": "soft",
          "race_class": "5",
          "track": "Sedgefield"
        },
        {
          "position": 1,
          "date": "2025-10-30",
          "distance": "2m190y",
          "going": "firm",
          "race_class": "5",
          "track": "Newcastle"
        },
        {
          "position": 8,
          "date": "2025-07-01",
          "distance": "1m4f104y",
          "going": "good",
          "race_class": "6",
          "track": "Musselburgh"
        },
        {
          "position": 5,
          "date": "2025-06-22",
          "distance": "2m48y",
          "going": "good",
          "race_class": "5",
          "track": "Hexham"
        }
      ]
    },
    {
      "rank": 4,
      "runner_name": "Snow Dragon",
      "number": 4,
      "draw": null,
      "age": 5,
      "weight": "11-4",
      "official_rating": 89,
      "jockey": "Gregor Walkingshaw",
      "trainer": "L Russell & M Scudamore",
      "odds_decimal": 9.0,
      "total_score": 50.4,
      "components": [
        {
          "name": "Market",
          "score": 15.6,
          "weight": 0.35,
          "weighted_score": 5.46,
          "reason": "Odds 9.0 (implied 11.1%)"
        },
        {
          "name": "Rating",
          "score": 76.7,
          "weight": 0.25,
          "weighted_score": 19.18,
          "reason": "OR 89 (field range 81-96)"
        },
        {
          "name": "Form",
          "score": 59.0,
          "weight": 0.2,
          "weighted_score": 11.8,
          "reason": "Recent positions: 4/3/3/3/6/4 (recency-weighted avg)"
        },
        {
          "name": "Suitability",
          "score": 76.7,
          "weight": 0.15,
          "weighted_score": 11.51,
          "reason": "3/6 runs at similar distance; 3/6 runs on similar going; 4/6 runs at Musselburgh"
        },
        {
          "name": "Connections",
          "score": 50.0,
          "weight": 0.05,
          "weighted_score": 2.5,
          "reason": "Connections: J: Gregor Walkingshaw, T: L Russell & M Scudamore (no win-rate stats available; neutral score)"
        }
      ],
      "recent_form": [
        {
          "position": 4,
          "date": "2026-01-27",
          "distance": "2m4f62y",
          "going": "heavy",
          "race_class": "5",
          "track": "Newcastle"
        },
        {
          "position": 3,
          "date": "2025-12-08",
          "distance": "2m3f171y",
          "going": "soft",
          "race_class": "5",
          "track": "Musselburgh"
        },
        {
          "position": 3,
          "date": "2025-11-28",
          "distance": "2m3f171y",
          "going": "good",
          "race_class": "5",
          "track": "Musselburgh"
        },
        {
          "position": 3,
          "date": "2025-10-21",
          "distance": "2m47y",
          "going": "soft",
          "race_class": "5",
          "track": "Perth"
        },
        {
          "position": 6,
          "date": "2025-02-16",
          "distance": "1m7f124y",
          "going": "good",
          "race_class": "5",
          "track": "Musselburgh"
        },
        {
          "position": 4,
          "date": "2025-01-01",
          "distance": "1m7f124y",
          "going": "good",
          "race_class": "4",
          "track": "Musselburgh"
        }
      ]
    },
    {
      "rank": 5,
      "runner_name": "Velvet Vulcan",
      "number": 7,
      "draw": null,
      "age": 7,
      "weight": "10-10",
      "official_rating": 81,
      "jockey": "Ben Smith",
      "trainer": "R M Smith",
      "odds_decimal": 4.33,
      "total_score": 48.3,
      "components": [
        {
          "name": "Market",
          "score": 32.3,
          "weight": 0.35,
          "weighted_score": 11.3,
          "reason": "Odds 4.3 (implied 23.1%)"
        },
        {
          "name": "Rating",
          "score": 50.0,
          "weight": 0.25,
          "weighted_score": 12.5,
          "reason": "OR 81 (field range 81-96)"
        },
        {
          "name": "Form",
          "score": 59.7,
          "weight": 0.2,
          "weighted_score": 11.94,
          "reason": "Recent positions: 2/2/4/6/6/5 (recency-weighted avg)"
        },
        {
          "name": "Suitability",
          "score": 66.7,
          "weight": 0.15,
          "weighted_score": 10.01,
          "reason": "3/6 runs at similar distance; 2/6 runs on similar going"
        },
        {
          "name": "Connections",
          "score": 50.0,
          "weight": 0.05,
          "weighted_score": 2.5,
          "reason": "Connections: J: Ben Smith, T: R M Smith (no win-rate stats available; neutral score)"
        }
      ],
      "recent_form": [
        {
          "position": 2,
          "date": "2026-02-10",
          "distance": "2m4f100y",
          "going": "soft",
          "race_class": "5",
          "track": "Ayr"
        },
        {
          "position": 2,
          "date": "2026-01-02",
          "distance": "2m4f100y",
          "going": "good",
          "race_class": "5",
          "track": "Ayr"
        },
        {
          "position": 4,
          "date": "2025-12-01",
          "distance": "2m3f110y",
          "going": "soft",
          "race_class": "5",
          "track": "Ayr"
        },
        {
          "position": 6,
          "date": "2025-11-01",
          "distance": "2m",
          "going": "soft",
          "race_class": "4",
          "track": "Ayr"
        },
        {
          "position": 6,
          "date": "2025-10-09",
          "distance": "1m5f26y",
          "going": "heavy",
          "race_class": "6",
          "track": "Ayr"
        },
        {
          "position": 5,
          "date": "2025-09-04",
          "distance": "1m7f169y",
          "going": "standard",
          "race_class": "6",
          "track": "Lingfield"
        }
      ]
    },
    {
      "rank": 6,
      "runner_name": "Beat The Retreat",
      "number": 5,
      "draw": null,
      "age": 7,
      "weight": "11-2",
      "official_rating": 87,
      "jockey": "Dominic Hislop",
      "trainer": "N W Alexander",
      "odds_decimal": 15.0,
      "total_score": 42.5,
      "components": [
        {
          "name": "Market",
          "score": 9.3,
          "weight": 0.35,
          "weighted_score": 3.25,
          "reason": "Odds 15.0 (implied 6.7%)"
        },
        {
          "name": "Rating",
          "score": 70.0,
          "weight": 0.25,
          "weighted_score": 17.5,
          "reason": "OR 87 (field range 81-96)"
        },
        {
          "name": "Form",
          "score": 34.8,
          "weight": 0.2,
          "weighted_score": 6.96,
          "reason": "Recent positions: 10/1/8/11/2/5 (recency-weighted avg)"
        },
        {
          "name": "Suitability",
          "score": 81.7,
          "weight": 0.15,
          "weighted_score": 12.26,
          "reason": "4/6 runs at similar distance; 5/6 runs on similar going; 1/6 runs at Musselburgh"
        },
        {
          "name": "Connections",
          "score": 50.0,
          "weight": 0.05,
          "weighted_score": 2.5,
          "reason": "Connections: J: Dominic Hislop, T: N W Alexander (no win-rate stats available; neutral score)"
        }
      ],
      "recent_form": [
        {
          "position": 10,
          "date": "2025-12-22",
          "distance": "2m7f180y",
          "going": "good",
          "race_class": "5",
          "track": "Musselburgh"
        },
        {
          "position": 1,
          "date": "2025-12-01",
          "distance": "2m3f110y",
          "going": "soft",
          "race_class": "5",
          "track": "Ayr"
        },
        {
          "position": 8,
          "date": "2025-07-03",
          "distance": "2m4f35y",
          "going": "good",
          "race_class": "5",
          "track": "Perth"
        },
        {
          "position": 11,
          "date": "2025-06-07",
          "distance": "2m4f28y",
          "going": "good",
          "race_class": "5",
          "track": "Hexham"
        },
        {
          "position": 2,
          "date": "2025-05-14",
          "distance": "2m4f35y",
          "going": "good",
          "race_class": "5",
          "track": "Perth"
        },
        {
          "position": 5,
          "date": "2025-04-23",
          "distance": "2m7f207y",
          "going": "good",
          "race_class": "5",
          "track": "Perth"
        }
      ]
    }
  ],
  "picks": {
    "top_pick": {
      "runner_name": "Cher Tara",
      "rank": 1,
      "score": 57.3
    },
    "backup_1": {
      "runner_name": "Gonnino",
      "rank": 2,
      "score": 54.5
    },
    "backup_2": {
      "runner_name": "National Question",
      "rank": 3,
      "score": 53.6
    }
  },
  "confidence": {
    "band": "LOW",
    "margin": 2.8,
    "reasons": [
      "Narrow margin of 2.8 pts"
    ]
  },
  "disclaimer": "These rankings represent statistical analysis only. They are not predictions or guarantees. Horse racing outcomes are inherently uncertain. Use for personal research only."
}