{
  "race_id": "taunton-2026-01-17-16-20",
  "meta": {
    "track": "Taunton",
    "date": "2026-01-17",
    "off_time": "16:20",
    "distance": "2m3f1y",
    "going": "soft",
    "race_class": null,
    "race_name": "16:20 Saturday 17 January 2026",
    "runners_count": 13,
    "prize": null,
    "surface": null
  },
  "runners": [
    {
      "rank": 1,
      "runner_name": "BEST NIGHT",
      "number": null,
      "draw": null,
      "age": 5,
      "weight": "11-13",
      "official_rating": 99,
      "rpr": null,
      "ts": null,
      "trainer_rtf": null,
      "days_since_last_run": null,
      "course_winner": null,
      "distance_winner": null,
      "cd_winner": null,
      "jockey": "Rian Corcoran(7)",
      "trainer": "David Pipe",
      "odds_decimal": 1.11,
      "total_score": 49.9,
      "components": [
        {
          "name": "Market",
          "score": 8.2,
          "weight": 0.5172,
          "weighted_score": 4.24,
          "reason": "Odds 1.11; fair win prob 8.2% (race-normalised)"
        },
        {
          "name": "Rating",
          "score": 100.0,
          "weight": 0.431,
          "weighted_score": 43.1,
          "reason": "OR 99 (field range 74\u201399)"
        },
        {
          "name": "Form",
          "score": null,
          "weight": 0,
          "weighted_score": 0,
          "reason": "No recent form data"
        },
        {
          "name": "Suitability",
          "score": null,
          "weight": 0,
          "weighted_score": 0,
          "reason": "No form to assess suitability"
        },
        {
          "name": "Freshness",
          "score": null,
          "weight": 0,
          "weighted_score": 0,
          "reason": "No last run date available"
        },
        {
          "name": "C/D Profile",
          "score": null,
          "weight": 0,
          "weighted_score": 0,
          "reason": "No C/D badge data available"
        },
        {
          "name": "Connections",
          "score": 50.0,
          "weight": 0.0517,
          "weighted_score": 2.59,
          "reason": "T: David Pipe, J: Rian Corcoran(7) (no RTF stats \u2014 neutral)"
        },
        {
          "name": "Mkt Expectation",
          "score": null,
          "weight": 0,
          "weighted_score": 0,
          "reason": "No last race data"
        }
      ],
      "recent_form": [],
      "last_race_fav": false,
      "last_race_beaten_fav": false,
      "last_race_joint_fav": false,
      "last_race_sp": null
    },
    {
      "rank": 2,
      "runner_name": "LITTLE LEDGEND",
      "number": null,
      "draw": null,
      "age": 6,
      "weight": "11-13",
      "official_rating": 99,
      "rpr": null,
      "ts": null,
      "trainer_rtf": null,
      "days_since_last_run": null,
      "course_winner": null,
      "distance_winner": null,
      "cd_winner": null,
      "jockey": "Sean Bowen",
      "trainer": "Olly Murphy",
      "odds_decimal": 1.16,
      "total_score": 49.8,
      "components": [
        {
          "name": "Market",
          "score": 7.9,
          "weight": 0.5172,
          "weighted_score": 4.09,
          "reason": "Odds 1.16; fair win prob 7.9% (race-normalised)"
        },
        {
          "name": "Rating",
          "score": 100.0,
          "weight": 0.431,
          "weighted_score": 43.1,
          "reason": "OR 99 (field range 74\u201399)"
        },
        {
          "name": "Form",
          "score": null,
          "weight": 0,
          "weighted_score": 0,
          "reason": "No recent form data"
        },
        {
          "name": "Suitability",
          "score": null,
          "weight": 0,
          "weighted_score": 0,
          "reason": "No form to assess suitability"
        },
        {
          "name": "Freshness",
          "score": null,
          "weight": 0,
          "weighted_score": 0,
          "reason": "No last run date available"
        },
        {
          "name": "C/D Profile",
          "score": null,
          "weight": 0,
          "weighted_score": 0,
          "reason": "No C/D badge data available"
        },
        {
          "name": "Connections",
          "score": 50.0,
          "weight": 0.0517,
          "weighted_score": 2.59,
          "reason": "T: Olly Murphy, J: Sean Bowen (no RTF stats \u2014 neutral)"
        },
        {
          "name": "Mkt Expectation",
          "score": null,
          "weight": 0,
          "weighted_score": 0,
          "reason": "No last race data"
        }
      ],
      "recent_form": [],
      "last_race_fav": false,
      "last_race_beaten_fav": false,
      "last_race_joint_fav": false,
      "last_race_sp": null
    },
    {
      "rank": 3,
      "runner_name": "BEL OMBRE",
      "number": null,
      "draw": null,
      "age": 6,
      "weight": "11-12",
      "official_rating": 98,
      "rpr": null,
      "ts": null,
      "trainer_rtf": null,
      "days_since_last_run": null,
      "course_winner": null,
      "distance_winner": null,
      "cd_winner": null,
      "jockey": "Conor O'Farrell",
      "trainer": "Neil Mulholland",
      "odds_decimal": 1.21,
      "total_score": 47.9,
      "components": [
        {
          "name": "Market",
          "score": 7.6,
          "weight": 0.5172,
          "weighted_score": 3.93,
          "reason": "Odds 1.21; fair win prob 7.6% (race-normalised)"
        },
        {
          "name": "Rating",
          "score": 96.0,
          "weight": 0.431,
          "weighted_score": 41.38,
          "reason": "OR 98 (field range 74\u201399)"
        },
        {
          "name": "Form",
          "score": null,
          "weight": 0,
          "weighted_score": 0,
          "reason": "No recent form data"
        },
        {
          "name": "Suitability",
          "score": null,
          "weight": 0,
          "weighted_score": 0,
          "reason": "No form to assess suitability"
        },
        {
          "name": "Freshness",
          "score": null,
          "weight": 0,
          "weighted_score": 0,
          "reason": "No last run date available"
        },
        {
          "name": "C/D Profile",
          "score": null,
          "weight": 0,
          "weighted_score": 0,
          "reason": "No C/D badge data available"
        },
        {
          "name": "Connections",
          "score": 50.0,
          "weight": 0.0517,
          "weighted_score": 2.59,
          "reason": "T: Neil Mulholland, J: Conor O'Farrell (no RTF stats \u2014 neutral)"
        },
        {
          "name": "Mkt Expectation",
          "score": null,
          "weight": 0,
          "weighted_score": 0,
          "reason": "No last race data"
        }
      ],
      "recent_form": [],
      "last_race_fav": false,
      "last_race_beaten_fav": false,
      "last_race_joint_fav": false,
      "last_race_sp": null
    },
    {
      "rank": 4,
      "runner_name": "PRAIRIE DIAMOND",
      "number": null,
      "draw": null,
      "age": 7,
      "weight": "11-7",
      "official_rating": 93,
      "rpr": null,
      "ts": null,
      "trainer_rtf": null,
      "days_since_last_run": null,
      "course_winner": null,
      "distance_winner": null,
      "cd_winner": null,
      "jockey": "Beau Morgan(5)",
      "trainer": "Martin Keighley",
      "odds_decimal": 1.42,
      "total_score": 38.7,
      "components": [
        {
          "name": "Market",
          "score": 6.4,
          "weight": 0.5172,
          "weighted_score": 3.31,
          "reason": "Odds 1.42; fair win prob 6.4% (race-normalised)"
        },
        {
          "name": "Rating",
          "score": 76.0,
          "weight": 0.431,
          "weighted_score": 32.76,
          "reason": "OR 93 (field range 74\u201399)"
        },
        {
          "name": "Form",
          "score": null,
          "weight": 0,
          "weighted_score": 0,
          "reason": "No recent form data"
        },
        {
          "name": "Suitability",
          "score": null,
          "weight": 0,
          "weighted_score": 0,
          "reason": "No form to assess suitability"
        },
        {
          "name": "Freshness",
          "score": null,
          "weight": 0,
          "weighted_score": 0,
          "reason": "No last run date available"
        },
        {
          "name": "C/D Profile",
          "score": null,
          "weight": 0,
          "weighted_score": 0,
          "reason": "No C/D badge data available"
        },
        {
          "name": "Connections",
          "score": 50.0,
          "weight": 0.0517,
          "weighted_score": 2.59,
          "reason": "T: Martin Keighley, J: Beau Morgan(5) (no RTF stats \u2014 neutral)"
        },
        {
          "name": "Mkt Expectation",
          "score": null,
          "weight": 0,
          "weighted_score": 0,
          "reason": "No last race data"
        }
      ],
      "recent_form": [],
      "last_race_fav": false,
      "last_race_beaten_fav": false,
      "last_race_joint_fav": false,
      "last_race_sp": null
    },
    {
      "rank": 5,
      "runner_name": "TARITINO",
      "number": null,
      "draw": null,
      "age": 6,
      "weight": "11-5",
      "official_rating": 91,
      "rpr": null,
      "ts": null,
      "trainer_rtf": null,
      "days_since_last_run": null,
      "course_winner": null,
      "distance_winner": null,
      "cd_winner": null,
      "jockey": "Taylor Fisher",
      "trainer": "Joe Tickle",
      "odds_decimal": 1.11,
      "total_score": 36.1,
      "components": [
        {
          "name": "Market",
          "score": 8.2,
          "weight": 0.5172,
          "weighted_score": 4.24,
          "reason": "Odds 1.11; fair win prob 8.2% (race-normalised)"
        },
        {
          "name": "Rating",
          "score": 68.0,
          "weight": 0.431,
          "weighted_score": 29.31,
          "reason": "OR 91 (field range 74\u201399)"
        },
        {
          "name": "Form",
          "score": null,
          "weight": 0,
          "weighted_score": 0,
          "reason": "No recent form data"
        },
        {
          "name": "Suitability",
          "score": null,
          "weight": 0,
          "weighted_score": 0,
          "reason": "No form to assess suitability"
        },
        {
          "name": "Freshness",
          "score": null,
          "weight": 0,
          "weighted_score": 0,
          "reason": "No last run date available"
        },
        {
          "name": "C/D Profile",
          "score": null,
          "weight": 0,
          "weighted_score": 0,
          "reason": "No C/D badge data available"
        },
        {
          "name": "Connections",
          "score": 50.0,
          "weight": 0.0517,
          "weighted_score": 2.59,
          "reason": "T: Joe Tickle, J: Taylor Fisher (no RTF stats \u2014 neutral)"
        },
        {
          "name": "Mkt Expectation",
          "score": null,
          "weight": 0,
          "weighted_score": 0,
          "reason": "No last race data"
        }
      ],
      "recent_form": [],
      "last_race_fav": false,
      "last_race_beaten_fav": false,
      "last_race_joint_fav": false,
      "last_race_sp": null
    },
    {
      "rank": 6,
      "runner_name": "MANCERO",
      "number": null,
      "draw": null,
      "age": 4,
      "weight": "10-3",
      "official_rating": 90,
      "rpr": null,
      "ts": null,
      "trainer_rtf": null,
      "days_since_last_run": null,
      "course_winner": null,
      "distance_winner": null,
      "cd_winner": null,
      "jockey": "Charlie Hammond",
      "trainer": "David Pipe",
      "odds_decimal": 1.15,
      "total_score": 34.3,
      "components": [
        {
          "name": "Market",
          "score": 7.9,
          "weight": 0.5172,
          "weighted_score": 4.09,
          "reason": "Odds 1.15; fair win prob 7.9% (race-normalised)"
        },
        {
          "name": "Rating",
          "score": 64.0,
          "weight": 0.431,
          "weighted_score": 27.59,
          "reason": "OR 90 (field range 74\u201399)"
        },
        {
          "name": "Form",
          "score": null,
          "weight": 0,
          "weighted_score": 0,
          "reason": "No recent form data"
        },
        {
          "name": "Suitability",
          "score": null,
          "weight": 0,
          "weighted_score": 0,
          "reason": "No form to assess suitability"
        },
        {
          "name": "Freshness",
          "score": null,
          "weight": 0,
          "weighted_score": 0,
          "reason": "No last run date available"
        },
        {
          "name": "C/D Profile",
          "score": null,
          "weight": 0,
          "weighted_score": 0,
          "reason": "No C/D badge data available"
        },
        {
          "name": "Connections",
          "score": 50.0,
          "weight": 0.0517,
          "weighted_score": 2.59,
          "reason": "T: David Pipe, J: Charlie Hammond (no RTF stats \u2014 neutral)"
        },
        {
          "name": "Mkt Expectation",
          "score": null,
          "weight": 0,
          "weighted_score": 0,
          "reason": "No last race data"
        }
      ],
      "recent_form": [],
      "last_race_fav": false,
      "last_race_beaten_fav": false,
      "last_race_joint_fav": false,
      "last_race_sp": null
    },
    {
      "rank": 7,
      "runner_name": "BIGZ BELIEF",
      "number": null,
      "draw": null,
      "age": 9,
      "weight": "11-3",
      "official_rating": 89,
      "rpr": null,
      "ts": null,
      "trainer_rtf": null,
      "days_since_last_run": null,
      "course_winner": null,
      "distance_winner": null,
      "cd_winner": null,
      "jockey": "Tom Broughton(5)",
      "trainer": "Fergal O'Brien",
      "odds_decimal": 1.11,
      "total_score": 32.7,
      "components": [
        {
          "name": "Market",
          "score": 8.2,
          "weight": 0.5172,
          "weighted_score": 4.24,
          "reason": "Odds 1.11; fair win prob 8.2% (race-normalised)"
        },
        {
          "name": "Rating",
          "score": 60.0,
          "weight": 0.431,
          "weighted_score": 25.86,
          "reason": "OR 89 (field range 74\u201399)"
        },
        {
          "name": "Form",
          "score": null,
          "weight": 0,
          "weighted_score": 0,
          "reason": "No recent form data"
        },
        {
          "name": "Suitability",
          "score": null,
          "weight": 0,
          "weighted_score": 0,
          "reason": "No form to assess suitability"
        },
        {
          "name": "Freshness",
          "score": null,
          "weight": 0,
          "weighted_score": 0,
          "reason": "No last run date available"
        },
        {
          "name": "C/D Profile",
          "score": null,
          "weight": 0,
          "weighted_score": 0,
          "reason": "No C/D badge data available"
        },
        {
          "name": "Connections",
          "score": 50.0,
          "weight": 0.0517,
          "weighted_score": 2.59,
          "reason": "T: Fergal O'Brien, J: Tom Broughton(5) (no RTF stats \u2014 neutral)"
        },
        {
          "name": "Mkt Expectation",
          "score": null,
          "weight": 0,
          "weighted_score": 0,
          "reason": "No last race data"
        }
      ],
      "recent_form": [],
      "last_race_fav": false,
      "last_race_beaten_fav": false,
      "last_race_joint_fav": false,
      "last_race_sp": null
    },
    {
      "rank": 8,
      "runner_name": "LUCKY BOUNCE",
      "number": null,
      "draw": null,
      "age": 9,
      "weight": "11-0",
      "official_rating": 86,
      "rpr": null,
      "ts": null,
      "trainer_rtf": null,
      "days_since_last_run": null,
      "course_winner": null,
      "distance_winner": null,
      "cd_winner": null,
      "jockey": "Conor Ring",
      "trainer": "Ryan Potter",
      "odds_decimal": 1.4,
      "total_score": 26.6,
      "components": [
        {
          "name": "Market",
          "score": 6.5,
          "weight": 0.5172,
          "weighted_score": 3.36,
          "reason": "Odds 1.40; fair win prob 6.5% (race-normalised)"
        },
        {
          "name": "Rating",
          "score": 48.0,
          "weight": 0.431,
          "weighted_score": 20.69,
          "reason": "OR 86 (field range 74\u201399)"
        },
        {
          "name": "Form",
          "score": null,
          "weight": 0,
          "weighted_score": 0,
          "reason": "No recent form data"
        },
        {
          "name": "Suitability",
          "score": null,
          "weight": 0,
          "weighted_score": 0,
          "reason": "No form to assess suitability"
        },
        {
          "name": "Freshness",
          "score": null,
          "weight": 0,
          "weighted_score": 0,
          "reason": "No last run date available"
        },
        {
          "name": "C/D Profile",
          "score": null,
          "weight": 0,
          "weighted_score": 0,
          "reason": "No C/D badge data available"
        },
        {
          "name": "Connections",
          "score": 50.0,
          "weight": 0.0517,
          "weighted_score": 2.59,
          "reason": "T: Ryan Potter, J: Conor Ring (no RTF stats \u2014 neutral)"
        },
        {
          "name": "Mkt Expectation",
          "score": null,
          "weight": 0,
          "weighted_score": 0,
          "reason": "No last race data"
        }
      ],
      "recent_form": [],
      "last_race_fav": false,
      "last_race_beaten_fav": false,
      "last_race_joint_fav": false,
      "last_race_sp": null
    },
    {
      "rank": 9,
      "runner_name": "COTTON END",
      "number": null,
      "draw": null,
      "age": 12,
      "weight": "10-10",
      "official_rating": 82,
      "rpr": null,
      "ts": null,
      "trainer_rtf": null,
      "days_since_last_run": null,
      "course_winner": null,
      "distance_winner": null,
      "cd_winner": null,
      "jockey": "Tabitha Worsley(3)",
      "trainer": "Jackie du Plessis",
      "odds_decimal": 1.33,
      "total_score": 19.9,
      "components": [
        {
          "name": "Market",
          "score": 6.9,
          "weight": 0.5172,
          "weighted_score": 3.57,
          "reason": "Odds 1.33; fair win prob 6.9% (race-normalised)"
        },
        {
          "name": "Rating",
          "score": 32.0,
          "weight": 0.431,
          "weighted_score": 13.79,
          "reason": "OR 82 (field range 74\u201399)"
        },
        {
          "name": "Form",
          "score": null,
          "weight": 0,
          "weighted_score": 0,
          "reason": "No recent form data"
        },
        {
          "name": "Suitability",
          "score": null,
          "weight": 0,
          "weighted_score": 0,
          "reason": "No form to assess suitability"
        },
        {
          "name": "Freshness",
          "score": null,
          "weight": 0,
          "weighted_score": 0,
          "reason": "No last run date available"
        },
        {
          "name": "C/D Profile",
          "score": null,
          "weight": 0,
          "weighted_score": 0,
          "reason": "No C/D badge data available"
        },
        {
          "name": "Connections",
          "score": 50.0,
          "weight": 0.0517,
          "weighted_score": 2.59,
          "reason": "T: Jackie du Plessis, J: Tabitha Worsley(3) (no RTF stats \u2014 neutral)"
        },
        {
          "name": "Mkt Expectation",
          "score": null,
          "weight": 0,
          "weighted_score": 0,
          "reason": "No last race data"
        }
      ],
      "recent_form": [],
      "last_race_fav": false,
      "last_race_beaten_fav": false,
      "last_race_joint_fav": false,
      "last_race_sp": null
    },
    {
      "rank": 10,
      "runner_name": "SAUCATS",
      "number": null,
      "draw": null,
      "age": 5,
      "weight": "10-4",
      "official_rating": 76,
      "rpr": null,
      "ts": null,
      "trainer_rtf": null,
      "days_since_last_run": null,
      "course_winner": null,
      "distance_winner": null,
      "cd_winner": null,
      "jockey": "Ben Godfrey",
      "trainer": "Joe Tickle",
      "odds_decimal": 1.25,
      "total_score": 9.8,
      "components": [
        {
          "name": "Market",
          "score": 7.3,
          "weight": 0.5172,
          "weighted_score": 3.78,
          "reason": "Odds 1.25; fair win prob 7.3% (race-normalised)"
        },
        {
          "name": "Rating",
          "score": 8.0,
          "weight": 0.431,
          "weighted_score": 3.45,
          "reason": "OR 76 (field range 74\u201399)"
        },
        {
          "name": "Form",
          "score": null,
          "weight": 0,
          "weighted_score": 0,
          "reason": "No recent form data"
        },
        {
          "name": "Suitability",
          "score": null,
          "weight": 0,
          "weighted_score": 0,
          "reason": "No form to assess suitability"
        },
        {
          "name": "Freshness",
          "score": null,
          "weight": 0,
          "weighted_score": 0,
          "reason": "No last run date available"
        },
        {
          "name": "C/D Profile",
          "score": null,
          "weight": 0,
          "weighted_score": 0,
          "reason": "No C/D badge data available"
        },
        {
          "name": "Connections",
          "score": 50.0,
          "weight": 0.0517,
          "weighted_score": 2.59,
          "reason": "T: Joe Tickle, J: Ben Godfrey (no RTF stats \u2014 neutral)"
        },
        {
          "name": "Mkt Expectation",
          "score": null,
          "weight": 0,
          "weighted_score": 0,
          "reason": "No last race data"
        }
      ],
      "recent_form": [],
      "last_race_fav": false,
      "last_race_beaten_fav": false,
      "last_race_joint_fav": false,
      "last_race_sp": null
    },
    {
      "rank": 11,
      "runner_name": "ABSOLUT GREY",
      "number": null,
      "draw": null,
      "age": 5,
      "weight": "10-2 (9-13)",
      "official_rating": 74,
      "rpr": null,
      "ts": null,
      "trainer_rtf": null,
      "days_since_last_run": null,
      "course_winner": null,
      "distance_winner": null,
      "cd_winner": null,
      "jockey": "James Davies",
      "trainer": "Dean Summersby",
      "odds_decimal": 1.09,
      "total_score": 6.9,
      "components": [
        {
          "name": "Market",
          "score": 8.4,
          "weight": 0.5172,
          "weighted_score": 4.34,
          "reason": "Odds 1.09; fair win prob 8.4% (race-normalised)"
        },
        {
          "name": "Rating",
          "score": 0.0,
          "weight": 0.431,
          "weighted_score": 0.0,
          "reason": "OR 74 (field range 74\u201399)"
        },
        {
          "name": "Form",
          "score": null,
          "weight": 0,
          "weighted_score": 0,
          "reason": "No recent form data"
        },
        {
          "name": "Suitability",
          "score": null,
          "weight": 0,
          "weighted_score": 0,
          "reason": "No form to assess suitability"
        },
        {
          "name": "Freshness",
          "score": null,
          "weight": 0,
          "weighted_score": 0,
          "reason": "No last run date available"
        },
        {
          "name": "C/D Profile",
          "score": null,
          "weight": 0,
          "weighted_score": 0,
          "reason": "No C/D badge data available"
        },
        {
          "name": "Connections",
          "score": 50.0,
          "weight": 0.0517,
          "weighted_score": 2.59,
          "reason": "T: Dean Summersby, J: James Davies (no RTF stats \u2014 neutral)"
        },
        {
          "name": "Mkt Expectation",
          "score": null,
          "weight": 0,
          "weighted_score": 0,
          "reason": "No last race data"
        }
      ],
      "recent_form": [],
      "last_race_fav": false,
      "last_race_beaten_fav": false,
      "last_race_joint_fav": false,
      "last_race_sp": null
    },
    {
      "rank": 12,
      "runner_name": "SAWPIT SIENNA",
      "number": null,
      "draw": null,
      "age": 11,
      "weight": "10-2",
      "official_rating": 74,
      "rpr": null,
      "ts": null,
      "trainer_rtf": null,
      "days_since_last_run": null,
      "course_winner": null,
      "distance_winner": null,
      "cd_winner": null,
      "jockey": "Robert Dunne",
      "trainer": "Samuel Drinkwater",
      "odds_decimal": 1.12,
      "total_score": 6.8,
      "components": [
        {
          "name": "Market",
          "score": 8.2,
          "weight": 0.5172,
          "weighted_score": 4.24,
          "reason": "Odds 1.12; fair win prob 8.2% (race-normalised)"
        },
        {
          "name": "Rating",
          "score": 0.0,
          "weight": 0.431,
          "weighted_score": 0.0,
          "reason": "OR 74 (field range 74\u201399)"
        },
        {
          "name": "Form",
          "score": null,
          "weight": 0,
          "weighted_score": 0,
          "reason": "No recent form data"
        },
        {
          "name": "Suitability",
          "score": null,
          "weight": 0,
          "weighted_score": 0,
          "reason": "No form to assess suitability"
        },
        {
          "name": "Freshness",
          "score": null,
          "weight": 0,
          "weighted_score": 0,
          "reason": "No last run date available"
        },
        {
          "name": "C/D Profile",
          "score": null,
          "weight": 0,
          "weighted_score": 0,
          "reason": "No C/D badge data available"
        },
        {
          "name": "Connections",
          "score": 50.0,
          "weight": 0.0517,
          "weighted_score": 2.59,
          "reason": "T: Samuel Drinkwater, J: Robert Dunne (no RTF stats \u2014 neutral)"
        },
        {
          "name": "Mkt Expectation",
          "score": null,
          "weight": 0,
          "weighted_score": 0,
          "reason": "No last race data"
        }
      ],
      "recent_form": [],
      "last_race_fav": false,
      "last_race_beaten_fav": false,
      "last_race_joint_fav": false,
      "last_race_sp": null
    },
    {
      "rank": 13,
      "runner_name": "POET'S REFLECTION",
      "number": null,
      "draw": null,
      "age": 11,
      "weight": "10-2 (9-8)",
      "official_rating": 74,
      "rpr": null,
      "ts": null,
      "trainer_rtf": null,
      "days_since_last_run": null,
      "course_winner": null,
      "distance_winner": null,
      "cd_winner": null,
      "jockey": "James Best",
      "trainer": "Linda Blackford",
      "odds_decimal": 1.11,
      "total_score": 6.8,
      "components": [
        {
          "name": "Market",
          "score": 8.2,
          "weight": 0.5172,
          "weighted_score": 4.24,
          "reason": "Odds 1.11; fair win prob 8.2% (race-normalised)"
        },
        {
          "name": "Rating",
          "score": 0.0,
          "weight": 0.431,
          "weighted_score": 0.0,
          "reason": "OR 74 (field range 74\u201399)"
        },
        {
          "name": "Form",
          "score": null,
          "weight": 0,
          "weighted_score": 0,
          "reason": "No recent form data"
        },
        {
          "name": "Suitability",
          "score": null,
          "weight": 0,
          "weighted_score": 0,
          "reason": "No form to assess suitability"
        },
        {
          "name": "Freshness",
          "score": null,
          "weight": 0,
          "weighted_score": 0,
          "reason": "No last run date available"
        },
        {
          "name": "C/D Profile",
          "score": null,
          "weight": 0,
          "weighted_score": 0,
          "reason": "No C/D badge data available"
        },
        {
          "name": "Connections",
          "score": 50.0,
          "weight": 0.0517,
          "weighted_score": 2.59,
          "reason": "T: Linda Blackford, J: James Best (no RTF stats \u2014 neutral)"
        },
        {
          "name": "Mkt Expectation",
          "score": null,
          "weight": 0,
          "weighted_score": 0,
          "reason": "No last race data"
        }
      ],
      "recent_form": [],
      "last_race_fav": false,
      "last_race_beaten_fav": false,
      "last_race_joint_fav": false,
      "last_race_sp": null
    }
  ],
  "picks": {
    "top_pick": {
      "runner_name": "BEST NIGHT",
      "rank": 1,
      "score": 49.9
    },
    "backup_1": {
      "runner_name": "LITTLE LEDGEND",
      "rank": 2,
      "score": 49.8
    },
    "backup_2": {
      "runner_name": "BEL OMBRE",
      "rank": 3,
      "score": 47.9
    }
  },
  "confidence": {
    "band": "LOW",
    "margin": 0.1,
    "reasons": [
      "Market prob gap 0.4 pts (race-normalised)",
      "3/8 scoring components available",
      "Total-score margin 0.1 pts"
    ]
  },
  "disclaimer": "These rankings represent statistical analysis only. They are not predictions or guarantees. Horse racing outcomes are inherently uncertain. Use for personal research only.",
  "_source_url": "https://www.timeform.com/horse-racing/result/taunton/2026-01-17/1620/49/7",
  "_date": "2026-01-17",
  "_result": {
    "status": "complete",
    "runners": [
      {
        "runner_name": "BEL OMBRE",
        "position": 1,
        "sp_decimal": 1.21,
        "sp_string": "85/403",
        "is_nr": false
      },
      {
        "runner_name": "LITTLE LEDGEND",
        "position": 2,
        "sp_decimal": 1.16,
        "sp_string": "13/82",
        "is_nr": false
      },
      {
        "runner_name": "PRAIRIE DIAMOND",
        "position": 3,
        "sp_decimal": 1.42,
        "sp_string": "11/26",
        "is_nr": false
      },
      {
        "runner_name": "BEST NIGHT",
        "position": 4,
        "sp_decimal": 1.11,
        "sp_string": "12/113",
        "is_nr": false
      },
      {
        "runner_name": "TARITINO",
        "position": 5,
        "sp_decimal": 1.11,
        "sp_string": "12/113",
        "is_nr": false
      },
      {
        "runner_name": "SAWPIT SIENNA",
        "position": 6,
        "sp_decimal": 1.12,
        "sp_string": "14/115",
        "is_nr": false
      },
      {
        "runner_name": "MANCERO",
        "position": 7,
        "sp_decimal": 1.15,
        "sp_string": "18/119",
        "is_nr": false
      },
      {
        "runner_name": "BIGZ BELIEF",
        "position": 8,
        "sp_decimal": 1.11,
        "sp_string": "12/113",
        "is_nr": false
      },
      {
        "runner_name": "SAUCATS",
        "position": 9,
        "sp_decimal": 1.25,
        "sp_string": "33/134",
        "is_nr": false
      },
      {
        "runner_name": "ABSOLUT GREY",
        "position": 10,
        "sp_decimal": 1.09,
        "sp_string": "100/1101",
        "is_nr": false
      },
      {
        "runner_name": "COTTON END",
        "position": 11,
        "sp_decimal": 1.33,
        "sp_string": "50/151",
        "is_nr": false
      },
      {
        "runner_name": "LUCKY BOUNCE",
        "position": 12,
        "sp_decimal": 1.4,
        "sp_string": "66/167",
        "is_nr": false
      },
      {
        "runner_name": "POET'S REFLECTION",
        "position": 13,
        "sp_decimal": 1.11,
        "sp_string": "125/1126",
        "is_nr": false
      }
    ]
  }
}